pulumi_xyz/__init__.py
pulumi_xyz/_utilities.py
pulumi_xyz/data_source.py
pulumi_xyz/provider.py
pulumi_xyz/pulumi-plugin.json
pulumi_xyz/py.typed
pulumi_xyz/resource.py
pulumi_xyz/config/__init__.py
pulumi_xyz/config/__init__.pyi
pulumi_xyz/config/vars.py
pulumi_xyz/region/__init__.py
pulumi_xyz/region/_enums.py
pulumi_xyz-1.1.369.dist-info/METADATA
pulumi_xyz-1.1.369.dist-info/WHEEL
pulumi_xyz-1.1.369.dist-info/top_level.txt
pulumi_xyz-1.1.369.dist-info/RECORD
